nonebot/adapters/github/__init__.py
nonebot/adapters/github/adapter.py
nonebot/adapters/github/bot.py
nonebot/adapters/github/compat.py
nonebot/adapters/github/config.py
nonebot/adapters/github/event/__init__.py
nonebot/adapters/github/event/_base.py
nonebot/adapters/github/event/_types.py
nonebot/adapters/github/event/branch_protection_configuration_disabled.py
nonebot/adapters/github/event/branch_protection_configuration_enabled.py
nonebot/adapters/github/event/branch_protection_rule_created.py
nonebot/adapters/github/event/branch_protection_rule_deleted.py
nonebot/adapters/github/event/branch_protection_rule_edited.py
nonebot/adapters/github/event/check_run_completed.py
nonebot/adapters/github/event/check_run_created.py
nonebot/adapters/github/event/check_run_requested_action.py
nonebot/adapters/github/event/check_run_rerequested.py
nonebot/adapters/github/event/check_suite_completed.py
nonebot/adapters/github/event/check_suite_requested.py
nonebot/adapters/github/event/check_suite_rerequested.py
nonebot/adapters/github/event/code_scanning_alert_appeared_in_branch.py
nonebot/adapters/github/event/code_scanning_alert_closed_by_user.py
nonebot/adapters/github/event/code_scanning_alert_created.py
nonebot/adapters/github/event/code_scanning_alert_fixed.py
nonebot/adapters/github/event/code_scanning_alert_reopened.py
nonebot/adapters/github/event/code_scanning_alert_reopened_by_user.py
nonebot/adapters/github/event/commit_comment.py
nonebot/adapters/github/event/create.py
nonebot/adapters/github/event/custom_property_created.py
nonebot/adapters/github/event/custom_property_deleted.py
nonebot/adapters/github/event/custom_property_updated.py
nonebot/adapters/github/event/custom_property_values.py
nonebot/adapters/github/event/delete.py
nonebot/adapters/github/event/dependabot_alert_auto_dismissed.py
nonebot/adapters/github/event/dependabot_alert_auto_reopened.py
nonebot/adapters/github/event/dependabot_alert_created.py
nonebot_adapter_github-0.5.0.dist-info/LICENSE
nonebot_adapter_github-0.5.0.dist-info/METADATA
nonebot_adapter_github-0.5.0.dist-info/WHEEL
nonebot_adapter_github-0.5.0.dist-info/RECORD
