Metadata-Version: 2.1
Name: nonebot-adapter-github
Version: 0.5.0
Summary: GitHub adapter for nonebot2
Home-page: https://github.com/nonebot/adapter-github
License: MIT
Keywords: bot,github,webhook
Author: yanyongyu
Author-email: yyy@nonebot.dev
Requires-Python: >=3.9,<4.0
Classifier: Development Status :: 5 - Production/Stable
Classifier: Framework :: Robot Framework
Classifier: Framework :: Robot Framework :: Library
Classifier: License :: OSI Approved :: MIT License
Classifier: Operating System :: OS Independent
Classifier: Programming Language :: Python :: 3
Classifier: Programming Language :: Python :: 3.9
Classifier: Programming Language :: Python :: 3.10
Classifier: Programming Language :: Python :: 3.11
Classifier: Programming Language :: Python :: 3.12
Classifier: Programming Language :: Python :: 3.13
Requires-Dist: githubkit[auth-app] (>=0.12.2,<0.13.0)
Requires-Dist: nonebot2 (>=2.2.0,<3.0.0)
Requires-Dist: pydantic (>=1.10.0,<3.0.0,!=2.5.0,!=2.5.1)
Project-URL: Documentation, https://github.com/nonebot/adapter-github
Project-URL: Repository, https://github.com/nonebot/adapter-github
